nmapxml/__init__.py
nmapxml/models.py
nmapxml/parsers.py
nmapxml-0.0.3.dist-info/LICENSE
nmapxml-0.0.3.dist-info/METADATA
nmapxml-0.0.3.dist-info/WHEEL
nmapxml-0.0.3.dist-info/top_level.txt
nmapxml-0.0.3.dist-info/RECORD
